hello_alina_package/hello.py
hello_alina_package-0.1.0.dist-info/METADATA
hello_alina_package-0.1.0.dist-info/WHEEL
hello_alina_package-0.1.0.dist-info/top_level.txt
hello_alina_package-0.1.0.dist-info/RECORD
