Metadata-Version: 2.1
Name: hello-alina-package
Version: 0.1.0
Summary: first_package
Home-page: UNKNOWN
Author: Alina
Author-email: alinarus45@yahoo.com
License: UNKNOWN
Platform: UNKNOWN
